LICENSE
MANIFEST.in
README.md
setup.py
RNAtools/__init__.py
RNAtools/graph.py
RNAtools/partAlign.pyx
RNAtools.egg-info/PKG-INFO
RNAtools.egg-info/SOURCES.txt
RNAtools.egg-info/dependency_links.txt
RNAtools.egg-info/entry_points.txt
RNAtools.egg-info/not-zip-safe
RNAtools.egg-info/top_level.txt
data/16SrRNA_1X1M7.xrna
data/5S.VARNA
data/5S.enzyme.txt
data/5S.gray.txt
data/5S.lines.txt
data/5S_differentialDirected.VARNA
data/5prime_745.ct
data/README.txt
data/cleanCT_edge_cases.ct
data/foo.ct
data/graphEnergy_1.ct
data/graphEnergy_1.energy.txt
data/graphEnergy_2.ct
data/graphEnergy_2.energy.txt
data/hsa-mir-199b.ct
data/hsa-mir-218-1_998.ct
data/hsa-mir-218-2_890.ct
data/hsa-mir-99b_999.ct
data/ref_MT.csv
data/ref_MT.fa
data/run_examples.sh
data/sequence_hsa-mir-380.txt
data/sequence_hsa-mir-383.txt
data/tester.ct
data/tester.dot
data/tester2.dot