Metadata-Version: 1.0
Name: RNAtools
Version: 0.8.5
Summary: Tools for working with RNA files.
Home-page: UNKNOWN
Author: Gregg M. Rice, Eric J. Ma, Varun Shivashankar
Author-email: gmr@unc.edu, ericmajinglong@gmail.com, varunshivashankar@gmail.com
License: MIT
Platform: UNKNOWN
